{{define "sydney"}}
{
  "message": "accurate",
  "cod": "200",
  "count": 10,
  "list": [
    {
      "id": 2147714,
      "name": "Sydney",
      "coord": {
        "lon": 151.207321,
        "lat": -33.867851
      },
      "main": {
        "temp": 294.15,
        "pressure": 1017,
        "humidity": 88,
        "temp_min": 294.15,
        "temp_max": 294.15
      },
      "dt": 1459247400,
      "wind": {
        "speed": 4.1,
        "deg": 210
      },
      "sys": {
        "country": ""
      },
      "clouds": {
        "all": 75
      },
      "weather": [
        {
          "id": 803,
          "main": "Clouds",
          "description": "broken clouds",
          "icon": "04n"
        }
      ]
    },
    {
      "id": 6619279,
      "name": "City of Sydney",
      "coord": {
        "lon": 151.208435,
        "lat": -33.867779
      },
      "main": {
        "temp": 294.15,
        "pressure": 1017,
        "humidity": 88,
        "temp_min": 294.15,
        "temp_max": 294.15
      },
      "dt": 1459247400,
      "wind": {
        "speed": 4.1,
        "deg": 210
      },
      "sys": {
        "country": ""
      },
      "clouds": {
        "all": 75
      },
      "weather": [
        {
          "id": 803,
          "main": "Clouds",
          "description": "broken clouds",
          "icon": "04n"
        }
      ]
    },
    {
      "id": 2163755,
      "name": "Haymarket",
      "coord": {
        "lon": 151.205261,
        "lat": -33.878681
      },
      "main": {
        "temp": 294.15,
        "pressure": 1017,
        "humidity": 88,
        "temp_min": 294.15,
        "temp_max": 294.15
      },
      "dt": 1459247400,
      "wind": {
        "speed": 4.1,
        "deg": 210
      },
      "sys": {
        "country": ""
      },
      "clouds": {
        "all": 75
      },
      "weather": [
        {
          "id": 803,
          "main": "Clouds",
          "description": "broken clouds",
          "icon": "04n"
        }
      ]
    },
    {
      "id": 2207754,
      "name": "Ultimo",
      "coord": {
        "lon": 151.196945,
        "lat": -33.878609
      },
      "main": {
        "temp": 294.15,
        "pressure": 1017,
        "humidity": 88,
        "temp_min": 294.15,
        "temp_max": 294.15
      },
      "dt": 1459249200,
      "wind": {
        "speed": 4.1,
        "deg": 210
      },
      "sys": {
        "country": ""
      },
      "clouds": {
        "all": 75
      },
      "weather": [
        {
          "id": 803,
          "main": "Clouds",
          "description": "broken clouds",
          "icon": "04n"
        }
      ]
    },
    {
      "id": 2169378,
      "name": "Darlinghurst",
      "coord": {
        "lon": 151.219254,
        "lat": -33.879391
      },
      "main": {
        "temp": 294.15,
        "pressure": 1017,
        "humidity": 88,
        "temp_min": 294.15,
        "temp_max": 294.15
      },
      "dt": 1459249200,
      "wind": {
        "speed": 4.1,
        "deg": 210
      },
      "sys": {
        "country": ""
      },
      "clouds": {
        "all": 75
      },
      "weather": [
        {
          "id": 803,
          "main": "Clouds",
          "description": "broken clouds",
          "icon": "04n"
        }
      ]
    },
    {
      "id": 2164123,
      "name": "Haberfield",
      "coord": {
        "lon": 151.199997,
        "lat": -33.883331
      },
      "main": {
        "temp": 294.15,
        "pressure": 1017,
        "humidity": 88,
        "temp_min": 294.15,
        "temp_max": 294.15
      },
      "dt": 1459249200,
      "wind": {
        "speed": 4.1,
        "deg": 210
      },
      "sys": {
        "country": ""
      },
      "clouds": {
        "all": 75
      },
      "weather": [
        {
          "id": 803,
          "main": "Clouds",
          "description": "broken clouds",
          "icon": "04n"
        }
      ]
    },
    {
      "id": 2147821,
      "name": "Surry Hills",
      "coord": {
        "lon": 151.212814,
        "lat": -33.883739
      },
      "main": {
        "temp": 294.15,
        "pressure": 1017,
        "humidity": 88,
        "temp_min": 294.15,
        "temp_max": 294.15
      },
      "dt": 1459247400,
      "wind": {
        "speed": 4.1,
        "deg": 210
      },
      "sys": {
        "country": ""
      },
      "clouds": {
        "all": 75
      },
      "weather": [
        {
          "id": 803,
          "main": "Clouds",
          "description": "broken clouds",
          "icon": "04n"
        }
      ]
    },
    {
      "id": 2161251,
      "name": "Kirribilli",
      "coord": {
        "lon": 151.216675,
        "lat": -33.849998
      },
      "main": {
        "temp": 294.15,
        "pressure": 1017,
        "humidity": 88,
        "temp_min": 294.15,
        "temp_max": 294.15
      },
      "dt": 1459249200,
      "wind": {
        "speed": 4.1,
        "deg": 210
      },
      "sys": {
        "country": ""
      },
      "clouds": {
        "all": 75
      },
      "weather": [
        {
          "id": 803,
          "main": "Clouds",
          "description": "broken clouds",
          "icon": "04n"
        }
      ]
    },
    {
      "id": 2177052,
      "name": "Balmain",
      "coord": {
        "lon": 151.183334,
        "lat": -33.866669
      },
      "main": {
        "temp": 294.15,
        "pressure": 1017,
        "humidity": 88,
        "temp_min": 294.15,
        "temp_max": 294.15
      },
      "dt": 1459249200,
      "wind": {
        "speed": 4.1,
        "deg": 210
      },
      "sys": {
        "country": ""
      },
      "clouds": {
        "all": 75
      },
      "weather": [
        {
          "id": 803,
          "main": "Clouds",
          "description": "broken clouds",
          "icon": "04n"
        }
      ]
    },
    {
      "id": 2171589,
      "name": "Chippendale",
      "coord": {
        "lon": 151.197449,
        "lat": -33.88673
      },
      "main": {
        "temp": 294.15,
        "pressure": 1017,
        "humidity": 88,
        "temp_min": 294.15,
        "temp_max": 294.15
      },
      "dt": 1459247400,
      "wind": {
        "speed": 4.1,
        "deg": 210
      },
      "sys": {
        "country": ""
      },
      "clouds": {
        "all": 75
      },
      "weather": [
        {
          "id": 803,
          "main": "Clouds",
          "description": "broken clouds",
          "icon": "04n"
        }
      ]
    }
  ]
}
{{end}}